frametree/common.py
frametree/file_system.py
frametree/axes/medimage.py
frametree/axes/samples.py
frametree/core/__init__.py
frametree/core/_version.py
frametree/core/axes.py
frametree/core/cell.py
frametree/core/column.py
frametree/core/entry.py
frametree/core/exceptions.py
frametree/core/licence.py
frametree/core/packaging.py
frametree/core/pipeline.py
frametree/core/quality.py
frametree/core/row.py
frametree/core/salience.py
frametree/core/serialize.py
frametree/core/tree.py
frametree/core/utils.py
frametree/core/cli/__init__.py
frametree/core/cli/base.py
frametree/core/cli/frameset.py
frametree/core/cli/processing.py
frametree/core/cli/store.py
frametree/core/cli/tests/test_cli_frameset.py
frametree/core/cli/tests/test_cli_processing.py
frametree/core/cli/tests/test_cli_store.py
frametree/core/frameset/__init__.py
frametree/core/frameset/base.py
frametree/core/frameset/metadata.py
frametree/core/store/__init__.py
frametree/core/store/base.py
frametree/core/store/local.py
frametree/core/store/remote.py
frametree/core/store/tests/test_id_handling.py
frametree/core/store/tests/test_store.py
frametree/core/tests/test_clinical_space.py
frametree/core/tests/test_data_column.py
frametree/core/tests/test_dataset.py
frametree/core/tests/test_pipeline.py
frametree/core/tests/test_row.py
frametree/core/tests/test_tree.py
frametree/core/tests/test_utils.py
frametree/testing/__init__.py
frametree/testing/axes.py
frametree/testing/blueprint.py
frametree/testing/store.py
frametree/testing/tasks.py
frametree/testing/tests/test_blueprint.py
frametree-0.16.1.dist-info/METADATA
frametree-0.16.1.dist-info/WHEEL
frametree-0.16.1.dist-info/entry_points.txt
frametree-0.16.1.dist-info/licenses/AUTHORS
frametree-0.16.1.dist-info/licenses/LICENSE
frametree-0.16.1.dist-info/RECORD
