Metadata-Version: 2.4
Name: frametree
Version: 0.16.1
Summary: Frametree: a framework for analysing datasets stored in trees of file objects "in-place"
Project-URL: documentation, https://frametree.readthedocs.io
Project-URL: homepage, https://frametree.readthedocs.io
Project-URL: repository, https://github.com/ArcanaFramework/frametree.git
Author-email: "Thomas G. Close" <tom.g.close@gmail.com>
Maintainer-email: "Thomas G. Close" <tom.g.close@gmail.com>
License: Creative Commons Attribution-NonCommercial-ShareAlike 4.0 International Public License
License-File: AUTHORS
License-File: LICENSE
Keywords: frametree
Classifier: Development Status :: 3 - Alpha
Classifier: Environment :: Console
Classifier: Intended Audience :: Science/Research
Classifier: License :: OSI Approved :: Apache Software License
Classifier: Operating System :: MacOS :: MacOS X
Classifier: Operating System :: POSIX :: Linux
Classifier: Programming Language :: Python :: 3.11
Classifier: Programming Language :: Python :: 3.12
Classifier: Programming Language :: Python :: 3.13
Classifier: Topic :: Scientific/Engineering
Requires-Python: >=3.11
Requires-Dist: attrs>=22.1.0
Requires-Dist: click-option-group>=0.5.5
Requires-Dist: click>=8.1.3
Requires-Dist: deepdiff>=3.3
Requires-Dist: fasteners>=0.18
Requires-Dist: fileformats-extras[application]>=0.2.0
Requires-Dist: fileformats>=0.8.5
Requires-Dist: importlib-metadata>=1.4
Requires-Dist: natsort>=8.4.0
Requires-Dist: pydra>=1.0a2
Requires-Dist: pyyaml>=6.0
Requires-Dist: setuptools
Provides-Extra: dev
Requires-Dist: black; extra == 'dev'
Requires-Dist: codespell; extra == 'dev'
Requires-Dist: flake8; extra == 'dev'
Requires-Dist: flake8-pyproject; extra == 'dev'
Requires-Dist: pre-commit; extra == 'dev'
Provides-Extra: docs
Requires-Dist: docutils>=0.10; extra == 'docs'
Requires-Dist: frametree-bids; extra == 'docs'
Requires-Dist: frametree-xnat; extra == 'docs'
Requires-Dist: furo>=2022.2.14.1; extra == 'docs'
Requires-Dist: mock>1.0; extra == 'docs'
Requires-Dist: numpydoc>=0.6.0; extra == 'docs'
Requires-Dist: packaging; extra == 'docs'
Requires-Dist: sphinx-argparse>=0.2.0; extra == 'docs'
Requires-Dist: sphinx-click>=3.1; extra == 'docs'
Requires-Dist: sphinx-togglebutton>=0.3.2; extra == 'docs'
Requires-Dist: sphinx>=2.1.2; extra == 'docs'
Provides-Extra: test
Requires-Dist: fileformats-extras[image]; extra == 'test'
Requires-Dist: fileformats-medimage-extras; extra == 'test'
Requires-Dist: pytest-cov>=2.12.1; extra == 'test'
Requires-Dist: pytest-env>=0.6.2; extra == 'test'
Requires-Dist: pytest-rerunfailures>=15.0; extra == 'test'
Requires-Dist: pytest>=6.2.5; extra == 'test'
